<?xml version="1.0" encoding="UTF-8"?>
<objects serializationModel="Studio.02.02.00">
	<object class="Event" id="{10b0e272-2b75-42cf-aff1-59ba017deea1}">
		<property name="name">
			<value>PartVoice_ann_168</value>
		</property>
		<property name="outputFormat">
			<value>0</value>
		</property>
		<relationship name="folder">
			<destination>{9d6cd37c-e171-4fa2-9daf-f7a04f44d8e3}</destination>
		</relationship>
		<relationship name="mixer">
			<destination>{5662676c-9713-4b83-96b4-1d718f9d0433}</destination>
		</relationship>
		<relationship name="masterTrack">
			<destination>{97158f80-ea16-4e40-bc28-f340ca166c05}</destination>
		</relationship>
		<relationship name="mixerInput">
			<destination>{7770fb38-8ca0-4e13-9a0a-01a78a1884b5}</destination>
		</relationship>
		<relationship name="automatableProperties">
			<destination>{04257b5d-edae-47e2-b283-163d74320db9}</destination>
		</relationship>
		<relationship name="markerTracks">
			<destination>{9c092201-2657-4d67-ad20-4ab9298fdc79}</destination>
		</relationship>
		<relationship name="groupTracks">
			<destination>{b7a1afae-b265-49f3-b116-71e523e2a673}</destination>
		</relationship>
		<relationship name="timeline">
			<destination>{86ce31d5-cd43-467d-999b-94af1d2db349}</destination>
		</relationship>
		<relationship name="banks">
			<destination>{ac96311c-5cd4-400a-8d75-85a30b5e0af8}</destination>
		</relationship>
	</object>
	<object class="EventMixer" id="{5662676c-9713-4b83-96b4-1d718f9d0433}">
		<relationship name="masterBus">
			<destination>{3aa36886-0a49-4a7f-ab17-fc9c920fe8a6}</destination>
		</relationship>
	</object>
	<object class="MasterTrack" id="{97158f80-ea16-4e40-bc28-f340ca166c05}">
		<relationship name="mixerGroup">
			<destination>{3aa36886-0a49-4a7f-ab17-fc9c920fe8a6}</destination>
		</relationship>
	</object>
	<object class="MixerInput" id="{7770fb38-8ca0-4e13-9a0a-01a78a1884b5}">
		<relationship name="effectChain">
			<destination>{6b656bc3-c853-438a-8dc5-9a77c3a3315d}</destination>
		</relationship>
		<relationship name="panner">
			<destination>{95b43e76-2dd7-4672-b71f-0e1287967a0e}</destination>
		</relationship>
		<relationship name="output">
			<destination>{db02b58a-ccdf-4c8a-98cd-b9cf084d9ea5}</destination>
		</relationship>
	</object>
	<object class="EventAutomatableProperties" id="{04257b5d-edae-47e2-b283-163d74320db9}" />
	<object class="MarkerTrack" id="{9c092201-2657-4d67-ad20-4ab9298fdc79}" />
	<object class="GroupTrack" id="{b7a1afae-b265-49f3-b116-71e523e2a673}">
		<relationship name="modules">
			<destination>{b5610c17-f119-4970-8889-30ab70cf6c8e}</destination>
		</relationship>
		<relationship name="mixerGroup">
			<destination>{907a2842-ddb9-4f45-be3b-7b4440cf80be}</destination>
		</relationship>
	</object>
	<object class="Timeline" id="{86ce31d5-cd43-467d-999b-94af1d2db349}">
		<relationship name="modules">
			<destination>{b5610c17-f119-4970-8889-30ab70cf6c8e}</destination>
		</relationship>
	</object>
	<object class="EventMixerMaster" id="{3aa36886-0a49-4a7f-ab17-fc9c920fe8a6}">
		<relationship name="modulators">
			<destination>{f03bab22-d9c2-4117-a361-23af395cfc1f}</destination>
		</relationship>
		<relationship name="effectChain">
			<destination>{8cce90f3-818e-4599-86f7-f7d72df836dc}</destination>
		</relationship>
		<relationship name="panner">
			<destination>{61ff5352-3b87-42f2-a70d-5af2169a27ee}</destination>
		</relationship>
		<relationship name="mixer">
			<destination>{5662676c-9713-4b83-96b4-1d718f9d0433}</destination>
		</relationship>
	</object>
	<object class="MixerBusEffectChain" id="{6b656bc3-c853-438a-8dc5-9a77c3a3315d}">
		<relationship name="effects">
			<destination>{ff989b2d-eb15-4e01-9081-0d0edc5d67b8}</destination>
		</relationship>
	</object>
	<object class="MixerBusPanner" id="{95b43e76-2dd7-4672-b71f-0e1287967a0e}" />
	<object class="SingleSound" id="{b5610c17-f119-4970-8889-30ab70cf6c8e}">
		<property name="length">
			<value>1.5637083333333333</value>
		</property>
		<relationship name="audioFile">
			<destination>{1b3e0260-8abc-467c-9af4-c733fda658d6}</destination>
		</relationship>
	</object>
	<object class="EventMixerGroup" id="{907a2842-ddb9-4f45-be3b-7b4440cf80be}">
		<property name="name">
			<value>Audio 1</value>
		</property>
		<relationship name="effectChain">
			<destination>{251d34f8-5bc0-4686-96d9-84f2ea897afd}</destination>
		</relationship>
		<relationship name="panner">
			<destination>{390660ee-26d2-4c9e-a25d-e766365a5a31}</destination>
		</relationship>
		<relationship name="output">
			<destination>{3aa36886-0a49-4a7f-ab17-fc9c920fe8a6}</destination>
		</relationship>
	</object>
	<object class="ADSRModulator" id="{f03bab22-d9c2-4117-a361-23af395cfc1f}">
		<property name="nameOfPropertyBeingModulated">
			<value>volume</value>
		</property>
		<property name="initialValue">
			<value>-80</value>
		</property>
		<property name="attackTime">
			<value>0</value>
		</property>
		<property name="releaseTime">
			<value>500</value>
		</property>
		<property name="finalValue">
			<value>-80</value>
		</property>
	</object>
	<object class="MixerBusEffectChain" id="{8cce90f3-818e-4599-86f7-f7d72df836dc}">
		<relationship name="effects">
			<destination>{3115f640-c0f4-4cb1-8bb1-8cfbfb8ab847}</destination>
		</relationship>
	</object>
	<object class="MixerBusPanner" id="{61ff5352-3b87-42f2-a70d-5af2169a27ee}" />
	<object class="MixerBusFader" id="{ff989b2d-eb15-4e01-9081-0d0edc5d67b8}" />
	<object class="MixerBusEffectChain" id="{251d34f8-5bc0-4686-96d9-84f2ea897afd}">
		<relationship name="effects">
			<destination>{bde48bde-f6e3-48f7-b97f-1859f4c74575}</destination>
		</relationship>
	</object>
	<object class="MixerBusPanner" id="{390660ee-26d2-4c9e-a25d-e766365a5a31}" />
	<object class="MixerBusFader" id="{3115f640-c0f4-4cb1-8bb1-8cfbfb8ab847}" />
	<object class="MixerBusFader" id="{bde48bde-f6e3-48f7-b97f-1859f4c74575}" />
</objects>
