<?xml version="1.0" encoding="UTF-8"?>
<objects serializationModel="Studio.02.02.00">
	<object class="Event" id="{3f5973d6-9777-4abb-a346-f53a386e2deb}">
		<property name="name">
			<value>Level1_C2_Boss_024_ann</value>
		</property>
		<property name="outputFormat">
			<value>0</value>
		</property>
		<relationship name="folder">
			<destination>{8d9a9325-0b8a-4154-9cfb-2b5797f997a6}</destination>
		</relationship>
		<relationship name="mixer">
			<destination>{42accea5-9885-4b09-a5b3-4734304672b8}</destination>
		</relationship>
		<relationship name="masterTrack">
			<destination>{3fa9d55e-8135-486b-89ca-97f63d7743a7}</destination>
		</relationship>
		<relationship name="mixerInput">
			<destination>{90c805ae-9e7b-484f-b962-8d7fad2179ce}</destination>
		</relationship>
		<relationship name="automatableProperties">
			<destination>{26c015e3-ef9a-4dc1-a555-64dafb34fcbc}</destination>
		</relationship>
		<relationship name="markerTracks">
			<destination>{3c6913c2-6d74-44a9-b2ed-e1faf499df98}</destination>
		</relationship>
		<relationship name="groupTracks">
			<destination>{d39763b2-ed42-404b-84fb-460727699cac}</destination>
		</relationship>
		<relationship name="timeline">
			<destination>{08f0ec85-28ea-47a5-bdf3-6376b5817e39}</destination>
		</relationship>
		<relationship name="banks">
			<destination>{ac96311c-5cd4-400a-8d75-85a30b5e0af8}</destination>
		</relationship>
	</object>
	<object class="EventMixer" id="{42accea5-9885-4b09-a5b3-4734304672b8}">
		<relationship name="masterBus">
			<destination>{9be39ac4-5be7-4963-9396-0d94139646fb}</destination>
		</relationship>
	</object>
	<object class="MasterTrack" id="{3fa9d55e-8135-486b-89ca-97f63d7743a7}">
		<relationship name="mixerGroup">
			<destination>{9be39ac4-5be7-4963-9396-0d94139646fb}</destination>
		</relationship>
	</object>
	<object class="MixerInput" id="{90c805ae-9e7b-484f-b962-8d7fad2179ce}">
		<relationship name="effectChain">
			<destination>{60486349-d09d-408f-84a2-afc25c66e080}</destination>
		</relationship>
		<relationship name="panner">
			<destination>{f8b1ef0f-48c1-4253-843c-c71c41f8b907}</destination>
		</relationship>
		<relationship name="output">
			<destination>{db02b58a-ccdf-4c8a-98cd-b9cf084d9ea5}</destination>
		</relationship>
	</object>
	<object class="EventAutomatableProperties" id="{26c015e3-ef9a-4dc1-a555-64dafb34fcbc}" />
	<object class="MarkerTrack" id="{3c6913c2-6d74-44a9-b2ed-e1faf499df98}" />
	<object class="GroupTrack" id="{d39763b2-ed42-404b-84fb-460727699cac}">
		<relationship name="modules">
			<destination>{98aa1a92-142c-4e81-9e9d-6d7df841054c}</destination>
		</relationship>
		<relationship name="mixerGroup">
			<destination>{aa26c052-81fb-4db7-a66c-9654a49c2c92}</destination>
		</relationship>
	</object>
	<object class="Timeline" id="{08f0ec85-28ea-47a5-bdf3-6376b5817e39}">
		<relationship name="modules">
			<destination>{98aa1a92-142c-4e81-9e9d-6d7df841054c}</destination>
		</relationship>
	</object>
	<object class="EventMixerMaster" id="{9be39ac4-5be7-4963-9396-0d94139646fb}">
		<relationship name="modulators">
			<destination>{377da1f8-51bd-4411-8e38-600769fe52cd}</destination>
		</relationship>
		<relationship name="effectChain">
			<destination>{36a8e829-4fa0-4f96-a1bc-49796bdb4ce1}</destination>
		</relationship>
		<relationship name="panner">
			<destination>{a933ab4f-7e6b-4da0-a460-6401515e4c7e}</destination>
		</relationship>
		<relationship name="mixer">
			<destination>{42accea5-9885-4b09-a5b3-4734304672b8}</destination>
		</relationship>
	</object>
	<object class="MixerBusEffectChain" id="{60486349-d09d-408f-84a2-afc25c66e080}">
		<relationship name="effects">
			<destination>{37cc81a2-a602-4c4a-bc5d-699a8874dd74}</destination>
		</relationship>
	</object>
	<object class="MixerBusPanner" id="{f8b1ef0f-48c1-4253-843c-c71c41f8b907}" />
	<object class="SingleSound" id="{98aa1a92-142c-4e81-9e9d-6d7df841054c}">
		<property name="length">
			<value>1.8999999999999999</value>
		</property>
		<relationship name="audioFile">
			<destination>{8c73530f-8248-44e2-bd76-455cb78e1fce}</destination>
		</relationship>
	</object>
	<object class="EventMixerGroup" id="{aa26c052-81fb-4db7-a66c-9654a49c2c92}">
		<property name="name">
			<value>Audio 1</value>
		</property>
		<relationship name="effectChain">
			<destination>{95c90799-b4a3-4bf8-a6d6-cb2e0d66ad6c}</destination>
		</relationship>
		<relationship name="panner">
			<destination>{fdc89360-dd88-46b5-ac51-7ffdac762fcc}</destination>
		</relationship>
		<relationship name="output">
			<destination>{9be39ac4-5be7-4963-9396-0d94139646fb}</destination>
		</relationship>
	</object>
	<object class="ADSRModulator" id="{377da1f8-51bd-4411-8e38-600769fe52cd}">
		<property name="nameOfPropertyBeingModulated">
			<value>volume</value>
		</property>
		<property name="initialValue">
			<value>-80</value>
		</property>
		<property name="attackTime">
			<value>0</value>
		</property>
		<property name="releaseTime">
			<value>500</value>
		</property>
		<property name="finalValue">
			<value>-80</value>
		</property>
	</object>
	<object class="MixerBusEffectChain" id="{36a8e829-4fa0-4f96-a1bc-49796bdb4ce1}">
		<relationship name="effects">
			<destination>{eaaa2b0c-2c0d-4e3d-8ea2-dab7965ec3cd}</destination>
		</relationship>
	</object>
	<object class="MixerBusPanner" id="{a933ab4f-7e6b-4da0-a460-6401515e4c7e}" />
	<object class="MixerBusFader" id="{37cc81a2-a602-4c4a-bc5d-699a8874dd74}" />
	<object class="MixerBusEffectChain" id="{95c90799-b4a3-4bf8-a6d6-cb2e0d66ad6c}">
		<relationship name="effects">
			<destination>{3299db9d-38cd-4e70-813b-4e64de3bec47}</destination>
		</relationship>
	</object>
	<object class="MixerBusPanner" id="{fdc89360-dd88-46b5-ac51-7ffdac762fcc}" />
	<object class="MixerBusFader" id="{eaaa2b0c-2c0d-4e3d-8ea2-dab7965ec3cd}" />
	<object class="MixerBusFader" id="{3299db9d-38cd-4e70-813b-4e64de3bec47}" />
</objects>
