<?xml version="1.0" encoding="UTF-8"?>
<objects serializationModel="Studio.02.02.00">
	<object class="Event" id="{5abd6560-399b-404b-ab2b-cdf4fead37db}">
		<property name="name">
			<value>Level2_C1_Boss_003_hh</value>
		</property>
		<property name="outputFormat">
			<value>0</value>
		</property>
		<relationship name="folder">
			<destination>{ec415b02-4346-4edd-87ae-9e64a69b6d20}</destination>
		</relationship>
		<relationship name="mixer">
			<destination>{edfd5c22-8a24-486b-88db-677447aac9fe}</destination>
		</relationship>
		<relationship name="masterTrack">
			<destination>{66e2455a-b274-4c33-8854-ef10c2057d6a}</destination>
		</relationship>
		<relationship name="mixerInput">
			<destination>{6420f3c4-5b64-4060-81fc-afdd1534aaf5}</destination>
		</relationship>
		<relationship name="automatableProperties">
			<destination>{495cda0f-5b54-440d-bf21-9ed10058c520}</destination>
		</relationship>
		<relationship name="markerTracks">
			<destination>{3a1139ea-182f-4b1b-af6d-dea2532836cb}</destination>
		</relationship>
		<relationship name="groupTracks">
			<destination>{5f1633a2-1ed5-4865-a32f-5c554a5b05f1}</destination>
		</relationship>
		<relationship name="timeline">
			<destination>{f1cc2f18-e61a-43c1-85ba-727698e6a104}</destination>
		</relationship>
		<relationship name="banks">
			<destination>{ac96311c-5cd4-400a-8d75-85a30b5e0af8}</destination>
		</relationship>
	</object>
	<object class="EventMixer" id="{edfd5c22-8a24-486b-88db-677447aac9fe}">
		<relationship name="masterBus">
			<destination>{06edeac7-9061-4b5e-ad61-571b3fe57f4e}</destination>
		</relationship>
	</object>
	<object class="MasterTrack" id="{66e2455a-b274-4c33-8854-ef10c2057d6a}">
		<relationship name="mixerGroup">
			<destination>{06edeac7-9061-4b5e-ad61-571b3fe57f4e}</destination>
		</relationship>
	</object>
	<object class="MixerInput" id="{6420f3c4-5b64-4060-81fc-afdd1534aaf5}">
		<relationship name="effectChain">
			<destination>{147ee7ba-1e7e-433c-a882-ee703f1ac550}</destination>
		</relationship>
		<relationship name="panner">
			<destination>{efda503e-9a34-47ce-b106-ed928ed843a0}</destination>
		</relationship>
		<relationship name="output">
			<destination>{41e06d36-8537-4e1e-9888-2aa3b9519fdb}</destination>
		</relationship>
	</object>
	<object class="EventAutomatableProperties" id="{495cda0f-5b54-440d-bf21-9ed10058c520}" />
	<object class="MarkerTrack" id="{3a1139ea-182f-4b1b-af6d-dea2532836cb}" />
	<object class="GroupTrack" id="{5f1633a2-1ed5-4865-a32f-5c554a5b05f1}">
		<relationship name="modules">
			<destination>{6fa1d801-e5bd-439d-bb55-6b5b2a05e805}</destination>
		</relationship>
		<relationship name="mixerGroup">
			<destination>{bf523615-bbac-41e6-bbcd-237c82964112}</destination>
		</relationship>
	</object>
	<object class="Timeline" id="{f1cc2f18-e61a-43c1-85ba-727698e6a104}">
		<relationship name="modules">
			<destination>{6fa1d801-e5bd-439d-bb55-6b5b2a05e805}</destination>
		</relationship>
	</object>
	<object class="EventMixerMaster" id="{06edeac7-9061-4b5e-ad61-571b3fe57f4e}">
		<relationship name="modulators">
			<destination>{aa98d543-0147-4a0e-8932-26067c4e8f17}</destination>
		</relationship>
		<relationship name="effectChain">
			<destination>{237f9297-e9d7-4ca0-8741-5fbdff8de706}</destination>
		</relationship>
		<relationship name="panner">
			<destination>{6589c10f-da7e-4884-914d-09453bde25f7}</destination>
		</relationship>
		<relationship name="mixer">
			<destination>{edfd5c22-8a24-486b-88db-677447aac9fe}</destination>
		</relationship>
	</object>
	<object class="MixerBusEffectChain" id="{147ee7ba-1e7e-433c-a882-ee703f1ac550}">
		<relationship name="effects">
			<destination>{615dfa88-5901-4a50-a11a-1291f8af7333}</destination>
		</relationship>
	</object>
	<object class="MixerBusPanner" id="{efda503e-9a34-47ce-b106-ed928ed843a0}" />
	<object class="SingleSound" id="{6fa1d801-e5bd-439d-bb55-6b5b2a05e805}">
		<property name="length">
			<value>0.91410416666666672</value>
		</property>
		<relationship name="audioFile">
			<destination>{3f94214a-ed64-4739-834d-8b7985da0b28}</destination>
		</relationship>
	</object>
	<object class="EventMixerGroup" id="{bf523615-bbac-41e6-bbcd-237c82964112}">
		<property name="name">
			<value>Audio 1</value>
		</property>
		<relationship name="effectChain">
			<destination>{cb9b836d-0b92-415b-90a4-c2c55bcbb20f}</destination>
		</relationship>
		<relationship name="panner">
			<destination>{38fb8d27-2ffe-46e1-b750-8566563fca9f}</destination>
		</relationship>
		<relationship name="output">
			<destination>{06edeac7-9061-4b5e-ad61-571b3fe57f4e}</destination>
		</relationship>
	</object>
	<object class="ADSRModulator" id="{aa98d543-0147-4a0e-8932-26067c4e8f17}">
		<property name="nameOfPropertyBeingModulated">
			<value>volume</value>
		</property>
		<property name="initialValue">
			<value>-80</value>
		</property>
		<property name="attackTime">
			<value>0</value>
		</property>
		<property name="releaseTime">
			<value>500</value>
		</property>
		<property name="finalValue">
			<value>-80</value>
		</property>
	</object>
	<object class="MixerBusEffectChain" id="{237f9297-e9d7-4ca0-8741-5fbdff8de706}">
		<relationship name="effects">
			<destination>{5ecb4aac-9c14-4cfe-b141-25f43d45910a}</destination>
		</relationship>
	</object>
	<object class="MixerBusPanner" id="{6589c10f-da7e-4884-914d-09453bde25f7}" />
	<object class="MixerBusFader" id="{615dfa88-5901-4a50-a11a-1291f8af7333}" />
	<object class="MixerBusEffectChain" id="{cb9b836d-0b92-415b-90a4-c2c55bcbb20f}">
		<relationship name="effects">
			<destination>{d9c5d68d-e8c0-442e-8fd1-4ad77196b63f}</destination>
		</relationship>
	</object>
	<object class="MixerBusPanner" id="{38fb8d27-2ffe-46e1-b750-8566563fca9f}" />
	<object class="MixerBusFader" id="{5ecb4aac-9c14-4cfe-b141-25f43d45910a}" />
	<object class="MixerBusFader" id="{d9c5d68d-e8c0-442e-8fd1-4ad77196b63f}" />
</objects>
