<?xml version="1.0" encoding="UTF-8"?>
<objects serializationModel="Studio.02.02.00">
	<object class="Event" id="{c1f9777d-3408-4160-9de8-c34818c4f807}">
		<property name="name">
			<value>Level4_C1_Dialog_065_ann</value>
		</property>
		<property name="outputFormat">
			<value>0</value>
		</property>
		<relationship name="folder">
			<destination>{8d9a9325-0b8a-4154-9cfb-2b5797f997a6}</destination>
		</relationship>
		<relationship name="mixer">
			<destination>{71c85e5c-3d09-4b75-94af-d694c588540d}</destination>
		</relationship>
		<relationship name="masterTrack">
			<destination>{9a1a89d9-32ad-4709-88ec-12c1eb3df504}</destination>
		</relationship>
		<relationship name="mixerInput">
			<destination>{66056c4b-8af7-448c-be55-95adfa6e0127}</destination>
		</relationship>
		<relationship name="automatableProperties">
			<destination>{2fdc7139-acc8-4a69-b4c5-039cb1e177e6}</destination>
		</relationship>
		<relationship name="markerTracks">
			<destination>{bcd7ca72-1664-489e-a658-2a5ffea2ee0d}</destination>
		</relationship>
		<relationship name="groupTracks">
			<destination>{8c65347c-17dd-4b59-b1b6-fe5068eb3431}</destination>
		</relationship>
		<relationship name="timeline">
			<destination>{410f9332-89a5-4cba-a33f-444f351df04a}</destination>
		</relationship>
		<relationship name="banks">
			<destination>{ac96311c-5cd4-400a-8d75-85a30b5e0af8}</destination>
		</relationship>
	</object>
	<object class="EventMixer" id="{71c85e5c-3d09-4b75-94af-d694c588540d}">
		<relationship name="masterBus">
			<destination>{749b2dfa-69a8-4958-a14b-efef14354567}</destination>
		</relationship>
	</object>
	<object class="MasterTrack" id="{9a1a89d9-32ad-4709-88ec-12c1eb3df504}">
		<relationship name="mixerGroup">
			<destination>{749b2dfa-69a8-4958-a14b-efef14354567}</destination>
		</relationship>
	</object>
	<object class="MixerInput" id="{66056c4b-8af7-448c-be55-95adfa6e0127}">
		<relationship name="effectChain">
			<destination>{d50fecc5-793d-4f45-86f0-225b58ec6ac1}</destination>
		</relationship>
		<relationship name="panner">
			<destination>{8b7a28cd-d389-48aa-82e1-cc2eed1c0b4c}</destination>
		</relationship>
		<relationship name="output">
			<destination>{db02b58a-ccdf-4c8a-98cd-b9cf084d9ea5}</destination>
		</relationship>
	</object>
	<object class="EventAutomatableProperties" id="{2fdc7139-acc8-4a69-b4c5-039cb1e177e6}" />
	<object class="MarkerTrack" id="{bcd7ca72-1664-489e-a658-2a5ffea2ee0d}" />
	<object class="GroupTrack" id="{8c65347c-17dd-4b59-b1b6-fe5068eb3431}">
		<relationship name="modules">
			<destination>{86180b33-d35e-4763-a071-d62f865ac8d9}</destination>
		</relationship>
		<relationship name="mixerGroup">
			<destination>{c5d33911-85f0-4c32-9e7b-410a930629b7}</destination>
		</relationship>
	</object>
	<object class="Timeline" id="{410f9332-89a5-4cba-a33f-444f351df04a}">
		<relationship name="modules">
			<destination>{86180b33-d35e-4763-a071-d62f865ac8d9}</destination>
		</relationship>
	</object>
	<object class="EventMixerMaster" id="{749b2dfa-69a8-4958-a14b-efef14354567}">
		<relationship name="modulators">
			<destination>{027d28fc-e1a5-4618-81d8-6a27a4862d1f}</destination>
		</relationship>
		<relationship name="effectChain">
			<destination>{d229ad9e-8ac4-4f39-98db-2921df11c051}</destination>
		</relationship>
		<relationship name="panner">
			<destination>{2cd53375-e34e-4e09-8286-619e7f85e100}</destination>
		</relationship>
		<relationship name="mixer">
			<destination>{71c85e5c-3d09-4b75-94af-d694c588540d}</destination>
		</relationship>
	</object>
	<object class="MixerBusEffectChain" id="{d50fecc5-793d-4f45-86f0-225b58ec6ac1}">
		<relationship name="effects">
			<destination>{e4a8321e-eb7b-49d0-9743-6c565afbda53}</destination>
		</relationship>
	</object>
	<object class="MixerBusPanner" id="{8b7a28cd-d389-48aa-82e1-cc2eed1c0b4c}" />
	<object class="SingleSound" id="{86180b33-d35e-4763-a071-d62f865ac8d9}">
		<property name="length">
			<value>3.7866666666666666</value>
		</property>
		<relationship name="audioFile">
			<destination>{b7fb4b82-69cc-46c8-bbba-b5d85fb61002}</destination>
		</relationship>
	</object>
	<object class="EventMixerGroup" id="{c5d33911-85f0-4c32-9e7b-410a930629b7}">
		<property name="name">
			<value>Audio 1</value>
		</property>
		<relationship name="effectChain">
			<destination>{6d613fcd-2790-4dd3-92a5-602531c23790}</destination>
		</relationship>
		<relationship name="panner">
			<destination>{3c055a5d-083a-4a09-b689-22bedfbf6fb2}</destination>
		</relationship>
		<relationship name="output">
			<destination>{749b2dfa-69a8-4958-a14b-efef14354567}</destination>
		</relationship>
	</object>
	<object class="ADSRModulator" id="{027d28fc-e1a5-4618-81d8-6a27a4862d1f}">
		<property name="nameOfPropertyBeingModulated">
			<value>volume</value>
		</property>
		<property name="initialValue">
			<value>-80</value>
		</property>
		<property name="attackTime">
			<value>0</value>
		</property>
		<property name="releaseTime">
			<value>500</value>
		</property>
		<property name="finalValue">
			<value>-80</value>
		</property>
	</object>
	<object class="MixerBusEffectChain" id="{d229ad9e-8ac4-4f39-98db-2921df11c051}">
		<relationship name="effects">
			<destination>{4a44f5d1-234d-4bc4-af45-2f7051569137}</destination>
		</relationship>
	</object>
	<object class="MixerBusPanner" id="{2cd53375-e34e-4e09-8286-619e7f85e100}" />
	<object class="MixerBusFader" id="{e4a8321e-eb7b-49d0-9743-6c565afbda53}" />
	<object class="MixerBusEffectChain" id="{6d613fcd-2790-4dd3-92a5-602531c23790}">
		<relationship name="effects">
			<destination>{a6ee7cae-7548-4219-a284-b89d61912b66}</destination>
		</relationship>
	</object>
	<object class="MixerBusPanner" id="{3c055a5d-083a-4a09-b689-22bedfbf6fb2}" />
	<object class="MixerBusFader" id="{4a44f5d1-234d-4bc4-af45-2f7051569137}" />
	<object class="MixerBusFader" id="{a6ee7cae-7548-4219-a284-b89d61912b66}" />
</objects>
