<?xml version="1.0" encoding="UTF-8"?>
<objects serializationModel="Studio.02.02.00">
	<object class="Event" id="{dc674631-b816-4823-b576-8ba5f7d0b0c8}">
		<property name="name">
			<value>Level4_C2_Boss_061_mimiko</value>
		</property>
		<property name="outputFormat">
			<value>0</value>
		</property>
		<relationship name="folder">
			<destination>{9dcae9aa-4fe3-4b60-9f71-2b8861b7cad2}</destination>
		</relationship>
		<relationship name="mixer">
			<destination>{2889cc8d-7ecc-49b5-b9c6-67ef8057a7f4}</destination>
		</relationship>
		<relationship name="masterTrack">
			<destination>{79bfe4b7-b03a-460f-a907-85df26979b06}</destination>
		</relationship>
		<relationship name="mixerInput">
			<destination>{a1d9e82a-529e-4402-9f02-f57d5a9a87a1}</destination>
		</relationship>
		<relationship name="automatableProperties">
			<destination>{6d4c400c-a89b-4c8f-9c76-0ca94c9f3e57}</destination>
		</relationship>
		<relationship name="markerTracks">
			<destination>{d040ac19-3a57-4241-aa9b-73b712e1f286}</destination>
		</relationship>
		<relationship name="groupTracks">
			<destination>{71c08703-4591-4f1a-8070-2f3d018b1d7e}</destination>
		</relationship>
		<relationship name="timeline">
			<destination>{ac66e71b-151f-4215-ad92-8f17666d1ce9}</destination>
		</relationship>
		<relationship name="banks">
			<destination>{ac96311c-5cd4-400a-8d75-85a30b5e0af8}</destination>
		</relationship>
	</object>
	<object class="EventMixer" id="{2889cc8d-7ecc-49b5-b9c6-67ef8057a7f4}">
		<relationship name="masterBus">
			<destination>{6eeaee70-7773-48e2-8fa0-651d770b9eff}</destination>
		</relationship>
	</object>
	<object class="MasterTrack" id="{79bfe4b7-b03a-460f-a907-85df26979b06}">
		<relationship name="mixerGroup">
			<destination>{6eeaee70-7773-48e2-8fa0-651d770b9eff}</destination>
		</relationship>
	</object>
	<object class="MixerInput" id="{a1d9e82a-529e-4402-9f02-f57d5a9a87a1}">
		<relationship name="effectChain">
			<destination>{111426ed-e5cf-4936-b92f-3bdaa8baf3fe}</destination>
		</relationship>
		<relationship name="panner">
			<destination>{e7bfa00b-c0c2-4b2c-a7f9-18f7d02af4df}</destination>
		</relationship>
		<relationship name="output">
			<destination>{7f58ab6b-3bd3-41ea-966a-04fbf6757386}</destination>
		</relationship>
	</object>
	<object class="EventAutomatableProperties" id="{6d4c400c-a89b-4c8f-9c76-0ca94c9f3e57}" />
	<object class="MarkerTrack" id="{d040ac19-3a57-4241-aa9b-73b712e1f286}" />
	<object class="GroupTrack" id="{71c08703-4591-4f1a-8070-2f3d018b1d7e}">
		<relationship name="modules">
			<destination>{6ec7a6af-0b59-4dcf-b5a7-35aca2087f91}</destination>
		</relationship>
		<relationship name="mixerGroup">
			<destination>{fcad585f-2c04-4037-8c49-492fa3d1fe03}</destination>
		</relationship>
	</object>
	<object class="Timeline" id="{ac66e71b-151f-4215-ad92-8f17666d1ce9}">
		<relationship name="modules">
			<destination>{6ec7a6af-0b59-4dcf-b5a7-35aca2087f91}</destination>
		</relationship>
	</object>
	<object class="EventMixerMaster" id="{6eeaee70-7773-48e2-8fa0-651d770b9eff}">
		<relationship name="modulators">
			<destination>{ceb9cb62-73f1-4f41-ae42-7cd0574e9ff3}</destination>
		</relationship>
		<relationship name="effectChain">
			<destination>{ca367cd9-b9ef-4e9f-88d8-07195fe8f1c3}</destination>
		</relationship>
		<relationship name="panner">
			<destination>{56bd46d4-6686-41ff-bbba-73f175d90aa2}</destination>
		</relationship>
		<relationship name="mixer">
			<destination>{2889cc8d-7ecc-49b5-b9c6-67ef8057a7f4}</destination>
		</relationship>
	</object>
	<object class="MixerBusEffectChain" id="{111426ed-e5cf-4936-b92f-3bdaa8baf3fe}">
		<relationship name="effects">
			<destination>{8d4a214e-af30-4764-9d7d-bdf393170a15}</destination>
		</relationship>
	</object>
	<object class="MixerBusPanner" id="{e7bfa00b-c0c2-4b2c-a7f9-18f7d02af4df}" />
	<object class="SingleSound" id="{6ec7a6af-0b59-4dcf-b5a7-35aca2087f91}">
		<property name="length">
			<value>2.4808541666666666</value>
		</property>
		<relationship name="audioFile">
			<destination>{e303d9ed-c07d-4bdd-a306-7080d8302c15}</destination>
		</relationship>
	</object>
	<object class="EventMixerGroup" id="{fcad585f-2c04-4037-8c49-492fa3d1fe03}">
		<property name="name">
			<value>Audio 1</value>
		</property>
		<relationship name="effectChain">
			<destination>{e7df58a6-a809-4883-9f38-dab4d34924e1}</destination>
		</relationship>
		<relationship name="panner">
			<destination>{b18a3ea3-fc81-4749-b7bd-a1aee504eeb1}</destination>
		</relationship>
		<relationship name="output">
			<destination>{6eeaee70-7773-48e2-8fa0-651d770b9eff}</destination>
		</relationship>
	</object>
	<object class="ADSRModulator" id="{ceb9cb62-73f1-4f41-ae42-7cd0574e9ff3}">
		<property name="nameOfPropertyBeingModulated">
			<value>volume</value>
		</property>
		<property name="initialValue">
			<value>-80</value>
		</property>
		<property name="attackTime">
			<value>0</value>
		</property>
		<property name="releaseTime">
			<value>500</value>
		</property>
		<property name="finalValue">
			<value>-80</value>
		</property>
	</object>
	<object class="MixerBusEffectChain" id="{ca367cd9-b9ef-4e9f-88d8-07195fe8f1c3}">
		<relationship name="effects">
			<destination>{cc44abf8-54a0-4c45-83a9-f61fed89008d}</destination>
		</relationship>
	</object>
	<object class="MixerBusPanner" id="{56bd46d4-6686-41ff-bbba-73f175d90aa2}" />
	<object class="MixerBusFader" id="{8d4a214e-af30-4764-9d7d-bdf393170a15}" />
	<object class="MixerBusEffectChain" id="{e7df58a6-a809-4883-9f38-dab4d34924e1}">
		<relationship name="effects">
			<destination>{4e008153-9946-4735-ac9c-d1773f649248}</destination>
		</relationship>
	</object>
	<object class="MixerBusPanner" id="{b18a3ea3-fc81-4749-b7bd-a1aee504eeb1}" />
	<object class="MixerBusFader" id="{cc44abf8-54a0-4c45-83a9-f61fed89008d}" />
	<object class="MixerBusFader" id="{4e008153-9946-4735-ac9c-d1773f649248}" />
</objects>
