<?xml version="1.0" encoding="UTF-8"?>
<objects serializationModel="Studio.02.02.00">
	<object class="AudioFile" id="{248308c4-b2e0-4017-9fb7-c2516184f058}">
		<property name="assetPath">
			<value>Voices/PV/安/PV_016_ann.wav</value>
		</property>
		<property name="frequencyInKHz">
			<value>48</value>
		</property>
		<property name="channelCount">
			<value>1</value>
		</property>
		<property name="length">
			<value>6.506875</value>
		</property>
		<relationship name="masterAssetFolder">
			<destination>{436ee973-a8ef-45e9-be9c-13ed6bbbd2c1}</destination>
		</relationship>
	</object>
</objects>
