<?xml version="1.0" encoding="UTF-8"?>
<objects serializationModel="Studio.02.02.00">
	<object class="AudioFile" id="{57feefa4-37a8-4758-9a7a-aeb7728efcd4}">
		<property name="assetPath">
			<value>Sound/Wood foley/-木頭-輕度扭曲-Footsteps, Human, Wooden Stairs, Very Creaky, Walk Down, Slow Tempo, On Axis SND89026 - Trimmed (5).wav</value>
		</property>
		<property name="frequencyInKHz">
			<value>192</value>
		</property>
		<property name="channelCount">
			<value>1</value>
		</property>
		<property name="length">
			<value>1.458375</value>
		</property>
		<relationship name="masterAssetFolder">
			<destination>{436ee973-a8ef-45e9-be9c-13ed6bbbd2c1}</destination>
		</relationship>
	</object>
</objects>
