<?xml version="1.0" encoding="UTF-8"?>
<objects serializationModel="Studio.02.02.00">
	<object class="AudioFile" id="{a3c65c54-4043-43b9-ae2e-76971f79cce7}">
		<property name="assetPath">
			<value>Voices/Dialogue/亜雅紗/Level/Level1_C2_Boss_064_agasa.wav</value>
		</property>
		<property name="frequencyInKHz">
			<value>48</value>
		</property>
		<property name="channelCount">
			<value>1</value>
		</property>
		<property name="length">
			<value>2.2647291666666667</value>
		</property>
		<relationship name="masterAssetFolder">
			<destination>{436ee973-a8ef-45e9-be9c-13ed6bbbd2c1}</destination>
		</relationship>
	</object>
</objects>
